<?xml version="1.0" encoding="UTF-8"?><record_update>
    <sys_choice action="DELETE" field="u_request_type" table="x_58872_needit_needit" version="3">
        <sys_choice_set action="DELETE">
            <element>u_request_type</element>
            <name>x_58872_needit_needit</name>
            <sys_class_name/>
            <sys_created_by>admin</sys_created_by>
            <sys_created_on/>
            <sys_id>aec1e2b5db210010414cdde748961951</sys_id>
            <sys_mod_count/>
            <sys_name>u_request_type</sys_name>
            <sys_package display_value="NeedIt" source="x_58872_needit">6ead8e780f603200cd674f8ce1050ed1</sys_package>
            <sys_policy/>
            <sys_scope display_value="NeedIt">6ead8e780f603200cd674f8ce1050ed1</sys_scope>
            <sys_update_name>sys_choice_x_58872_needit_needit_u_request_type</sys_update_name>
            <sys_updated_by>admin</sys_updated_by>
            <sys_updated_on>2020-01-13 17:48:34</sys_updated_on>
        </sys_choice_set>
        <sys_update_version action="INSERT_OR_UPDATE">
            <action>DELETE</action>
            <application/>
            <file_path/>
            <instance_id>78e02e5bdb07938452e3f70fbf96192b</instance_id>
            <instance_name>dev63868</instance_name>
            <name>sys_choice_x_58872_needit_needit_u_request_type</name>
            <payload><![CDATA[<?xml version="1.0" encoding="UTF-8"?><record_update><sys_choice action="DELETE" field="u_request_type" table="x_58872_needit_needit" version="3"><sys_choice_set action="DELETE"><element>u_request_type</element><name>x_58872_needit_needit</name><sys_class_name/><sys_created_by/><sys_created_on/><sys_id/><sys_mod_count/><sys_name/><sys_package/><sys_policy/><sys_scope/><sys_update_name/><sys_updated_by/><sys_updated_on>2019-12-06 22:48:45</sys_updated_on></sys_choice_set></sys_choice></record_update>]]></payload>
            <payload_hash>1828161538</payload_hash>
            <record_name>Task.u_request_type</record_name>
            <reverted_from/>
            <source>a4271c41db910010414cdde748961909</source>
            <source_table>sys_update_set</source_table>
            <state>previous</state>
            <sys_created_by>admin</sys_created_by>
            <sys_created_on>2019-12-06 22:48:45</sys_created_on>
            <sys_id>a4c162b5db210010414cdde748961957</sys_id>
            <sys_mod_count>0</sys_mod_count>
            <sys_recorded_at>16edd66b2040000001</sys_recorded_at>
            <sys_updated_by>admin</sys_updated_by>
            <sys_updated_on>2019-12-06 22:48:45</sys_updated_on>
            <type>Choice list</type>
            <update_guid>20c162b57321001082cc2937cf090257</update_guid>
            <update_guid_history>20c162b57321001082cc2937cf090257:1828161538,acc162b5f62100103f890bb824263f53:-103233526,ecc162b510210010356418e7dbe2b150:-854501905,20c162b510210010738832e542dbde4e:878753447,3c28ec05ecd100108036b580958ba22c:411213506</update_guid_history>
        </sys_update_version>
        <sys_metadata_delete action="INSERT_OR_UPDATE">
            <sys_audit_delete/>
            <sys_class_name>sys_metadata_delete</sys_class_name>
            <sys_created_by>admin</sys_created_by>
            <sys_created_on>2019-12-06 22:48:54</sys_created_on>
            <sys_db_object display_value="" name="sys_choice_set">sys_choice_set</sys_db_object>
            <sys_id>aec1e2b5db210010414cdde748961951</sys_id>
            <sys_metadata>aec1e2b5db210010414cdde748961951</sys_metadata>
            <sys_mod_count>0</sys_mod_count>
            <sys_name>u_request_type</sys_name>
            <sys_package display_value="NeedIt" source="x_58872_needit">6ead8e780f603200cd674f8ce1050ed1</sys_package>
            <sys_parent/>
            <sys_policy/>
            <sys_scope display_value="NeedIt">6ead8e780f603200cd674f8ce1050ed1</sys_scope>
            <sys_scope_delete display_value="">94872a8897db403e8ee69a431de2fca4</sys_scope_delete>
            <sys_update_name>sys_choice_x_58872_needit_needit_u_request_type</sys_update_name>
            <sys_update_version display_value="sys_choice_x_58872_needit_needit_u_request_type">a4c162b5db210010414cdde748961957</sys_update_version>
            <sys_updated_by>admin</sys_updated_by>
            <sys_updated_on>2019-12-06 22:48:54</sys_updated_on>
        </sys_metadata_delete>
    </sys_choice>
    <sys_update_version action="INSERT_OR_UPDATE">
        <action>DELETE</action>
        <application display_value="NeedIt">6ead8e780f603200cd674f8ce1050ed1</application>
        <file_path/>
        <instance_id>78e02e5bdb07938452e3f70fbf96192b</instance_id>
        <instance_name>dev63868</instance_name>
        <name>sys_choice_x_58872_needit_needit_u_request_type</name>
        <payload>&lt;?xml version="1.0" encoding="UTF-8"?&gt;&lt;record_update&gt;&lt;sys_choice action="DELETE" field="u_request_type" table="x_58872_needit_needit" version="3"&gt;&lt;sys_choice_set action="DELETE"&gt;&lt;element&gt;u_request_type&lt;/element&gt;&lt;name&gt;x_58872_needit_needit&lt;/name&gt;&lt;sys_class_name/&gt;&lt;sys_created_by&gt;admin&lt;/sys_created_by&gt;&lt;sys_created_on/&gt;&lt;sys_id&gt;aec1e2b5db210010414cdde748961951&lt;/sys_id&gt;&lt;sys_mod_count/&gt;&lt;sys_name&gt;u_request_type&lt;/sys_name&gt;&lt;sys_package display_value="NeedIt" source="x_58872_needit"&gt;6ead8e780f603200cd674f8ce1050ed1&lt;/sys_package&gt;&lt;sys_policy/&gt;&lt;sys_scope display_value="NeedIt"&gt;6ead8e780f603200cd674f8ce1050ed1&lt;/sys_scope&gt;&lt;sys_update_name&gt;sys_choice_x_58872_needit_needit_u_request_type&lt;/sys_update_name&gt;&lt;sys_updated_by&gt;admin&lt;/sys_updated_by&gt;&lt;sys_updated_on&gt;2020-01-13 17:48:34&lt;/sys_updated_on&gt;&lt;/sys_choice_set&gt;&lt;sys_update_version action="INSERT_OR_UPDATE"&gt;&lt;action&gt;DELETE&lt;/action&gt;&lt;application/&gt;&lt;file_path/&gt;&lt;instance_id&gt;78e02e5bdb07938452e3f70fbf96192b&lt;/instance_id&gt;&lt;instance_name&gt;dev63868&lt;/instance_name&gt;&lt;name&gt;sys_choice_x_58872_needit_needit_u_request_type&lt;/name&gt;&lt;payload&gt;&lt;![CDATA[&lt;?xml version="1.0" encoding="UTF-8"?&gt;&lt;record_update&gt;&lt;sys_choice action="DELETE" field="u_request_type" table="x_58872_needit_needit" version="3"&gt;&lt;sys_choice_set action="DELETE"&gt;&lt;element&gt;u_request_type&lt;/element&gt;&lt;name&gt;x_58872_needit_needit&lt;/name&gt;&lt;sys_class_name/&gt;&lt;sys_created_by/&gt;&lt;sys_created_on/&gt;&lt;sys_id/&gt;&lt;sys_mod_count/&gt;&lt;sys_name/&gt;&lt;sys_package/&gt;&lt;sys_policy/&gt;&lt;sys_scope/&gt;&lt;sys_update_name/&gt;&lt;sys_updated_by/&gt;&lt;sys_updated_on&gt;2019-12-06 22:48:45&lt;/sys_updated_on&gt;&lt;/sys_choice_set&gt;&lt;/sys_choice&gt;&lt;/record_update&gt;]]&gt;&lt;/payload&gt;&lt;payload_hash&gt;1828161538&lt;/payload_hash&gt;&lt;record_name&gt;Task.u_request_type&lt;/record_name&gt;&lt;reverted_from/&gt;&lt;source&gt;a4271c41db910010414cdde748961909&lt;/source&gt;&lt;source_table&gt;sys_update_set&lt;/source_table&gt;&lt;state&gt;previous&lt;/state&gt;&lt;sys_created_by&gt;admin&lt;/sys_created_by&gt;&lt;sys_created_on&gt;2019-12-06 22:48:45&lt;/sys_created_on&gt;&lt;sys_id&gt;a4c162b5db210010414cdde748961957&lt;/sys_id&gt;&lt;sys_mod_count&gt;0&lt;/sys_mod_count&gt;&lt;sys_recorded_at&gt;16edd66b2040000001&lt;/sys_recorded_at&gt;&lt;sys_updated_by&gt;admin&lt;/sys_updated_by&gt;&lt;sys_updated_on&gt;2019-12-06 22:48:45&lt;/sys_updated_on&gt;&lt;type&gt;Choice list&lt;/type&gt;&lt;update_guid&gt;20c162b57321001082cc2937cf090257&lt;/update_guid&gt;&lt;update_guid_history&gt;20c162b57321001082cc2937cf090257:1828161538,acc162b5f62100103f890bb824263f53:-103233526,ecc162b510210010356418e7dbe2b150:-854501905,20c162b510210010738832e542dbde4e:878753447,3c28ec05ecd100108036b580958ba22c:411213506&lt;/update_guid_history&gt;&lt;/sys_update_version&gt;&lt;sys_metadata_delete action="INSERT_OR_UPDATE"&gt;&lt;sys_audit_delete/&gt;&lt;sys_class_name&gt;sys_metadata_delete&lt;/sys_class_name&gt;&lt;sys_created_by&gt;admin&lt;/sys_created_by&gt;&lt;sys_created_on&gt;2019-12-06 22:48:54&lt;/sys_created_on&gt;&lt;sys_db_object display_value="" name="sys_choice_set"&gt;sys_choice_set&lt;/sys_db_object&gt;&lt;sys_id&gt;aec1e2b5db210010414cdde748961951&lt;/sys_id&gt;&lt;sys_metadata&gt;aec1e2b5db210010414cdde748961951&lt;/sys_metadata&gt;&lt;sys_mod_count&gt;0&lt;/sys_mod_count&gt;&lt;sys_name&gt;u_request_type&lt;/sys_name&gt;&lt;sys_package display_value="NeedIt" source="x_58872_needit"&gt;6ead8e780f603200cd674f8ce1050ed1&lt;/sys_package&gt;&lt;sys_parent/&gt;&lt;sys_policy/&gt;&lt;sys_scope display_value="NeedIt"&gt;6ead8e780f603200cd674f8ce1050ed1&lt;/sys_scope&gt;&lt;sys_scope_delete display_value=""&gt;94872a8897db403e8ee69a431de2fca4&lt;/sys_scope_delete&gt;&lt;sys_update_name&gt;sys_choice_x_58872_needit_needit_u_request_type&lt;/sys_update_name&gt;&lt;sys_update_version display_value="sys_choice_x_58872_needit_needit_u_request_type"&gt;a4c162b5db210010414cdde748961957&lt;/sys_update_version&gt;&lt;sys_updated_by&gt;admin&lt;/sys_updated_by&gt;&lt;sys_updated_on&gt;2019-12-06 22:48:54&lt;/sys_updated_on&gt;&lt;/sys_metadata_delete&gt;&lt;/sys_choice&gt;&lt;/record_update&gt;</payload>
        <payload_hash>-154017326</payload_hash>
        <record_name>x_58872_needit_needit.u_request_type</record_name>
        <reverted_from/>
        <source>97d1eaf1db210010414cdde74896192a</source>
        <source_table>sys_update_set</source_table>
        <state>previous</state>
        <sys_created_by>admin</sys_created_by>
        <sys_created_on>2020-01-13 17:48:34</sys_created_on>
        <sys_id>02798906db520010414cdde74896194a</sys_id>
        <sys_mod_count>0</sys_mod_count>
        <sys_recorded_at>16fa00586e60000001</sys_recorded_at>
        <sys_updated_by>admin</sys_updated_by>
        <sys_updated_on>2020-01-13 17:48:34</sys_updated_on>
        <type>Choice list</type>
        <update_guid>8a79890672520010d72813b85f7da549</update_guid>
        <update_guid_history>8a79890672520010d72813b85f7da549:-154017326,0e798906435200106e282f5fd5819a45:-1701966180,8a7989063a5200109ccf770d5647ea42:736548692,0a798906a4520010c959472ad860253f:833312879,83c126b5d4210010e2aa5053249d9a1d:0,20c162b57321001082cc2937cf090257:1828161538,acc162b5f62100103f890bb824263f53:-103233526,ecc162b510210010356418e7dbe2b150:-854501905,20c162b510210010738832e542dbde4e:878753447,3c28ec05ecd100108036b580958ba22c:411213506</update_guid_history>
    </sys_update_version>
    <sys_metadata_delete action="INSERT_OR_UPDATE">
        <sys_audit_delete/>
        <sys_class_name>sys_metadata_delete</sys_class_name>
        <sys_created_by>admin</sys_created_by>
        <sys_created_on>2020-01-13 17:48:43</sys_created_on>
        <sys_db_object display_value="" name="sys_choice_set">sys_choice_set</sys_db_object>
        <sys_id>48890d06db520010414cdde7489619b5</sys_id>
        <sys_metadata>48890d06db520010414cdde7489619b5</sys_metadata>
        <sys_mod_count>0</sys_mod_count>
        <sys_name>u_request_type</sys_name>
        <sys_package display_value="NeedIt" source="x_58872_needit">6ead8e780f603200cd674f8ce1050ed1</sys_package>
        <sys_parent/>
        <sys_policy/>
        <sys_scope display_value="NeedIt">6ead8e780f603200cd674f8ce1050ed1</sys_scope>
        <sys_scope_delete display_value="">94872a8897db403e8ee69a431de2fca4</sys_scope_delete>
        <sys_update_name>sys_choice_x_58872_needit_needit_u_request_type</sys_update_name>
        <sys_update_version display_value="sys_choice_x_58872_needit_needit_u_request_type">02798906db520010414cdde74896194a</sys_update_version>
        <sys_updated_by>admin</sys_updated_by>
        <sys_updated_on>2020-01-13 17:48:43</sys_updated_on>
    </sys_metadata_delete>
</record_update>
